{
    "LION": {
        "type": "result",
        "timestamp": "2020-02-02T00:00:33Z",
        "ping": {
            "jitter": 0.589,
            "latency": 92.019
        },
        "download": {
            "bandwidth": 11733423,
            "bytes": 124811400,
            "elapsed": 11004
        },
        "upload": {
            "bandwidth": 3909321,
            "bytes": 52164320,
            "elapsed": 13701
        },
        "packetLoss": 0,
        "isp": "Mauritius Telecom",
        "server": {
            "id": 17987,
            "name": "TELMA",
            "location": "Antananarivo",
            "country": "MG",
            "host": "speedtest.telma.mg",
            "port": 8080,
            "ip": "41.188.35.93"
        },
        "result": {
            "id": "6d4d79e7-4721-44c6-8394-2f0e0598d068",
            "url": "https://www.speedtest.net/result/c/6d4d79e7-4721-44c6-8394-2f0e0598d068"
        }
    },
    "SAFE1": {
        "type": "result",
        "timestamp": "2020-02-02T00:01:11Z",
        "ping": {
            "jitter": 0.606,
            "latency": 320.953
        },
        "download": {
            "bandwidth": 10738870,
            "bytes": 118993278,
            "elapsed": 15010
        },
        "upload": {
            "bandwidth": 3567386,
            "bytes": 47647768,
            "elapsed": 15006
        },
        "packetLoss": 0,
        "isp": "Mauritius Telecom",
        "server": {
            "id": 24682,
            "name": "Vodafone India",
            "location": "Cochin",
            "country": "India",
            "host": "ooklatestcochin.live.vodafone.in",
            "port": 8080,
            "ip": "112.79.47.25"
        },
        "result": {
            "id": "92ea7cc1-bbe7-49bc-9e87-d5107e971477",
            "url": "https://www.speedtest.net/result/c/92ea7cc1-bbe7-49bc-9e87-d5107e971477"
        }
    },
    "SAFE2": {
        "type": "result",
        "timestamp": "2020-02-02T00:01:35Z",
        "ping": {
            "jitter": 0.122,
            "latency": 55.062
        },
        "download": {
            "bandwidth": 12186907,
            "bytes": 128304400,
            "elapsed": 10815
        },
        "upload": {
            "bandwidth": 4224035,
            "bytes": 43555408,
            "elapsed": 10510
        },
        "packetLoss": 0,
        "isp": "Mauritius Telecom",
        "server": {
            "id": 1285,
            "name": "Vodacom Business",
            "location": "Durban",
            "country": "South Africa",
            "host": "speedtest.dne.vodacombusiness.co.za",
            "port": 8080,
            "ip": "41.0.144.228"
        },
        "result": {
            "id": "165cbd75-2c50-4a9b-b536-219cba5fb80c",
            "url": "https://www.speedtest.net/result/c/165cbd75-2c50-4a9b-b536-219cba5fb80c"
        }
    },
    "SAFE3": {
        "type": "result",
        "timestamp": "2020-02-02T00:02:05Z",
        "ping": {
            "jitter": 2.298,
            "latency": 98.492
        },
        "download": {
            "bandwidth": 1819897,
            "bytes": 25830000,
            "elapsed": 15008
        },
        "upload": {
            "bandwidth": 4034449,
            "bytes": 45742456,
            "elapsed": 11700
        },
        "packetLoss": 0,
        "isp": "Mauritius Telecom",
        "server": {
            "id": 12544,
            "name": "MyKRIS Asia Sdn Bhd",
            "location": "Penang",
            "country": "Malaysia",
            "host": "pngspeedtest.mykris.net",
            "port": 8080,
            "ip": "122.0.31.38"
        },
        "result": {
            "id": "2cdf612d-c951-4a0d-9d8e-6f5f039f9a81",
            "url": "https://www.speedtest.net/result/c/2cdf612d-c951-4a0d-9d8e-6f5f039f9a81"
        }
    },
    "MARS": {
        "type": "result",
        "timestamp": "2020-02-02T00:02:37Z",
        "ping": {
            "jitter": 0.184,
            "latency": 139.492
        },
        "download": {
            "bandwidth": 13310613,
            "bytes": 164462200,
            "elapsed": 13513
        },
        "upload": {
            "bandwidth": 3720862,
            "bytes": 52640048,
            "elapsed": 14606
        },
        "packetLoss": 0,
        "isp": "Mauritius Telecom",
        "server": {
            "id": 27454,
            "name": "Emtel Ltd",
            "location": "Port Mathurin",
            "country": "Mauritius",
            "host": "speedtest5-1g.emtelnet.com",
            "port": 8080,
            "ip": "102.163.98.18"
        },
        "result": {
            "id": "98075274-45c7-47e3-8a90-c93fe4c4a5f0",
            "url": "https://www.speedtest.net/result/c/98075274-45c7-47e3-8a90-c93fe4c4a5f0"
        }
    }
}